yaqd_ni/VERSION
yaqd_ni/__init__.py
yaqd_ni/__version__.py
yaqd_ni/_ni_daqmx_tmux.py
yaqd_ni/ni-daqmx-tmux.avpr
yaqd_ni/ni-daqmx-tmux.toml
yaqd_ni-2023.12.0.dist-info/entry_points.txt
yaqd_ni-2023.12.0.dist-info/LICENSE
yaqd_ni-2023.12.0.dist-info/WHEEL
yaqd_ni-2023.12.0.dist-info/METADATA
yaqd_ni-2023.12.0.dist-info/RECORD
